<?xml version="1.0" encoding="UTF-8" standalone="yes"?>
<scenarioConfiguration  domain="ISAnalytics" name="RegionExcessLoginAlert" scenario="RegionExcessLoginAlert">
    <description>Send alerts when authentication requests from a particular region exceed a certain number</description>
    <parameterMap>
        <entry>
            <key>timeWindow</key>
            <value>1000</value>
        </entry>
        <entry>
            <key>maxRequestCount</key>
            <value>100</value>
        </entry>
    </parameterMap>
</scenarioConfiguration>